AUTHORS
ChangeLog
Dockerfile.py27-build
Dockerfile.py36-build
LICENSE
Makefile
Makefile.internal
README.md
artifacts.yaml
pylintrc
requirements.txt
setup.cfg
setup.py
skipper.yaml
test-requirements.txt
docker_test_tools/__init__.py
docker_test_tools/api_version.py
docker_test_tools/base_test.py
docker_test_tools/config.py
docker_test_tools/environment.py
docker_test_tools/logs.py
docker_test_tools/plugin.py
docker_test_tools/stats.py
docker_test_tools/utils.py
docker_test_tools/wiremock.py
docker_test_tools.egg-info/PKG-INFO
docker_test_tools.egg-info/SOURCES.txt
docker_test_tools.egg-info/dependency_links.txt
docker_test_tools.egg-info/not-zip-safe
docker_test_tools.egg-info/pbr.json
docker_test_tools.egg-info/requires.txt
docker_test_tools.egg-info/top_level.txt
tests/__init__.py
tests/integration/__init__.py
tests/integration/conftest.py
tests/integration/nose2.cfg
tests/integration/pytest.cfg
tests/integration/test_example.py
tests/resources/docker-compose-v2.1.yml
tests/resources/docker-compose-v2.yml
tests/resources/ut/requests-journal.json
tests/resources/wiremock_stubs/example.json
tests/ut/__init__.py
tests/ut/nose2.cfg
tests/ut/test_config.py
tests/ut/test_environment.py
tests/ut/test_logs.py
tests/ut/test_utils.py
tests/ut/test_wiremock.py