Metadata-Version: 1.1
Name: docker-test-tools
Version: 1.3.0
Summary: Make it easy to write tests that relies on docker containers environment
Home-page: http://github.com/stratoscale/docker-test-tools.git
Author: Stratoscale
Author-email: support@stratoscale.com
License: MIT
Platform: UNKNOWN
Classifier: Operating System :: POSIX :: Linux
Classifier: Programming Language :: Python
Classifier: Programming Language :: Python :: 2
Classifier: Programming Language :: Python :: 2.7
